repctl/__init__.py
repctl/__main__.py
repctl/exceptions.py
repctl/py.typed
repctl/snippets.py
repctl/sysreptor.py
repctl/utils.py
repctl/findings/__init__.py
repctl/findings/loaders/scuba.py
repctl-0.2.0.dist-info/METADATA
repctl-0.2.0.dist-info/WHEEL
repctl-0.2.0.dist-info/entry_points.txt
repctl-0.2.0.dist-info/licenses/LICENSE
repctl-0.2.0.dist-info/RECORD
