Metadata-Version: 2.4
Name: repctl
Version: 0.2.0
Summary: An alternative CLI and API-Client for sysReptor
Project-URL: Repository, https://github.com/NiklasBeierl/repctl
License-File: LICENSE
Classifier: Development Status :: 2 - Pre-Alpha
Classifier: Environment :: Console
Classifier: Intended Audience :: Developers
Classifier: Operating System :: Unix
Classifier: Programming Language :: Python
Classifier: Programming Language :: Python :: 3 :: Only
Classifier: Programming Language :: Python :: 3.13
Classifier: Topic :: Security
Requires-Python: >=3.13
Requires-Dist: python-dotenv>=1.1.0
Requires-Dist: pyyaml>=6.0.2
Requires-Dist: requests-toolbelt>=1.0.0
